samoosa/__init__.py
samoosa/logic.py
samoosa/samoosa.py
samoosa/summary_ai.py
samoosa/youtube_subtitle.py
samoosa-13.0.dist-info/LICENSE
samoosa-13.0.dist-info/METADATA
samoosa-13.0.dist-info/WHEEL
samoosa-13.0.dist-info/entry_points.txt
samoosa-13.0.dist-info/top_level.txt
samoosa-13.0.dist-info/RECORD
