Metadata-Version: 2.1
Name: samoosa
Version: 13.0
Summary: Samoosa is an innovative Python-based tool designed to provide concise and comprehensive summaries of YouTube videos.
Home-page: https://github.com/PRANAV-S-V/samoosa-tool.git
Author: Pranav S V
Author-email: thisispranavsv@yahoo.com
Classifier: Programming Language :: Python :: 3
Classifier: License :: OSI Approved :: MIT License
Classifier: Operating System :: OS Independent
Requires-Python: >=3.6
License-File: LICENSE
Requires-Dist: google-generativeai (>=0.1.0)
Requires-Dist: python-dotenv (>=1.0.1)
Requires-Dist: youtube-transcript-api (>=0.4.4)
